macroscope.py
lib/decorators.py
lib/enums.py
lib/globals.py
lib/commands/closest.py
lib/commands/co_occurrence.py
lib/commands/context_change.py
lib/commands/context_network.py
lib/commands/drift.py
lib/commands/frequency.py
lib/commands/sentiment.py
lib/commands/synonym_network.py
lib/dataStructures/Coord.py
lib/dataStructures/Word.py
lib/dataStructures/closest/ClosestResponse.py
lib/dataStructures/closest/ClosestWord.py
lib/dataStructures/contextChange/ContextChangeResponse.py
lib/dataStructures/contextChange/ContextChangeWord.py
lib/dataStructures/contextNetwork/ContextNetwork.py
lib/dataStructures/contextNetwork/ContextNetworkEdge.py
lib/dataStructures/contextNetwork/ContextNetworkNode.py
lib/dataStructures/contextNetwork/ContextNetworkResponse.py
lib/dataStructures/cooccurrence/CooccurrenceContextWord.py
lib/dataStructures/cooccurrence/CooccurrenceDatumPoint.py
lib/dataStructures/cooccurrence/CooccurrenceResponse.py
lib/dataStructures/drift/DriftResponse.py
lib/dataStructures/drift/SemanticDriftPoints.py
lib/dataStructures/drift/WordPoint.py
lib/dataStructures/drift/YearPoint.py
lib/dataStructures/frequency/FrequencyCoords.py
lib/dataStructures/frequency/FrequencyResponse.py
lib/dataStructures/sentiment/SentimentResponse.py
lib/dataStructures/synonymNetwork/SynonymNetwork.py
lib/dataStructures/synonymNetwork/SynonymNetworkEdge.py
lib/dataStructures/synonymNetwork/SynonymNetworkNode.py
lib/dataStructures/synonymNetwork/SynonymNetworkResponse.py
lib/handlers/ClosestResponseHandler.py
lib/handlers/ContextChangeResponseHandler.py
lib/handlers/ContextNetworkResponseHandler.py
lib/handlers/CooccurrenceResponseHandler.py
lib/handlers/DriftResponseHandler.py
lib/handlers/FrequencyResponseHandler.py
lib/handlers/SentimentHandler.py
lib/handlers/SynonymNetworkResponseHandler.py
lib/utils/DataReader.py
lib/utils/SerialiseClassObjectToJson.py
lib/utils/getDataDirPath.py
lib/utils/jsonfs.py
lib/utils/partitionInterval.py
lib/utils/roundToDecade.py
macroscope-0.1.1.dist-info/METADATA
macroscope-0.1.1.dist-info/WHEEL
macroscope-0.1.1.dist-info/entry_points.txt
macroscope-0.1.1.dist-info/top_level.txt
macroscope-0.1.1.dist-info/RECORD
