Metadata-Version: 2.1
Name: macroscope
Version: 0.1.1
Summary: The macroscope command line interface
Home-page: UNKNOWN
Author: StraightOuttaCrompton
Author-email: soc@email.com
License: UNKNOWN
Platform: UNKNOWN
Requires-Python: >=3.0.*
Requires-Dist: click
Requires-Dist: matplotlib
Requires-Dist: networkx
Requires-Dist: numpy
Requires-Dist: pandas
Requires-Dist: python-louvain
Requires-Dist: sklearn
Provides-Extra: dev
Requires-Dist: autopep8 ; extra == 'dev'
Requires-Dist: flake8 ; extra == 'dev'
Requires-Dist: rope ; extra == 'dev'
Requires-Dist: wheel ; extra == 'dev'
